treedata/__init__.py
treedata/_utils.py
treedata/_core/__init__.py
treedata/_core/aligned_mapping.py
treedata/_core/merge.py
treedata/_core/read.py
treedata/_core/treedata.py
treedata/_core/write.py
treedata-0.2.4.dist-info/METADATA
treedata-0.2.4.dist-info/WHEEL
treedata-0.2.4.dist-info/licenses/LICENSE
treedata-0.2.4.dist-info/RECORD
